odoo/addons/pos_minimize_menu/README.rst
odoo/addons/pos_minimize_menu/__init__.py
odoo/addons/pos_minimize_menu/__manifest__.py
odoo/addons/pos_minimize_menu/demo/pos_config.xml
odoo/addons/pos_minimize_menu/i18n/es.po
odoo/addons/pos_minimize_menu/i18n/fr.po
odoo/addons/pos_minimize_menu/i18n/it.po
odoo/addons/pos_minimize_menu/i18n/pos_minimize_menu.pot
odoo/addons/pos_minimize_menu/models/__init__.py
odoo/addons/pos_minimize_menu/models/pos_config.py
odoo/addons/pos_minimize_menu/models/res_config_settings.py
odoo/addons/pos_minimize_menu/readme/CONFIGURE.rst
odoo/addons/pos_minimize_menu/readme/CONTRIBUTORS.rst
odoo/addons/pos_minimize_menu/readme/DESCRIPTION.rst
odoo/addons/pos_minimize_menu/readme/DEVELOP.rst
odoo/addons/pos_minimize_menu/static/description/icon.png
odoo/addons/pos_minimize_menu/static/description/index.html
odoo/addons/pos_minimize_menu/static/img/configure_important_buttons.png
odoo/addons/pos_minimize_menu/static/img/important_buttons_displayed.png
odoo/addons/pos_minimize_menu/static/img/with_module.png
odoo/addons/pos_minimize_menu/static/img/without_module.png
odoo/addons/pos_minimize_menu/static/src/js/ProductScreen.js
odoo/addons/pos_minimize_menu/static/src/xml/ProductScreen.xml
odoo/addons/pos_minimize_menu/views/view_res_config_settings.xml
odoo_addon_pos_minimize_menu-16.0.1.0.0.7.dist-info/METADATA
odoo_addon_pos_minimize_menu-16.0.1.0.0.7.dist-info/WHEEL
odoo_addon_pos_minimize_menu-16.0.1.0.0.7.dist-info/top_level.txt
odoo_addon_pos_minimize_menu-16.0.1.0.0.7.dist-info/RECORD
